phenotype_ontologies/__init__.py
phenotype_ontologies/admin.py
phenotype_ontologies/app_settings.py
phenotype_ontologies/apps.py
phenotype_ontologies/choices.py
phenotype_ontologies/filters.py
phenotype_ontologies/managers.py
phenotype_ontologies/models.py
phenotype_ontologies/serializers.py
phenotype_ontologies/urls.py
phenotype_ontologies/views.py
phenotype_ontologies/viewsets.py
phenotype_ontologies/management/__init__.py
phenotype_ontologies/management/commands/__init__.py
phenotype_ontologies/management/commands/sync_ontology.py
phenotype_ontologies/migrations/0001_initial.py
phenotype_ontologies/migrations/0002_auto_20180726_1213.py
phenotype_ontologies/migrations/__init__.py
django_phenotype_ontologies-1.1.0.dist-info/AUTHORS.rst
django_phenotype_ontologies-1.1.0.dist-info/LICENSE
django_phenotype_ontologies-1.1.0.dist-info/METADATA
django_phenotype_ontologies-1.1.0.dist-info/WHEEL
django_phenotype_ontologies-1.1.0.dist-info/top_level.txt
django_phenotype_ontologies-1.1.0.dist-info/RECORD
