Metadata-Version: 2.1
Name: django-phenotype-ontologies
Version: 1.1.0
Summary: Django app to parse/load phenotype ontologies (OncoTree, HPO, MONDO, etc)
Home-page: https://github.com/genomics-geek/django-phenotype-ontologies
Author: Michael A. Gonzalez
Author-email: GonzalezMA@email.chop.edu
License: MIT
Keywords: django-phenotype-ontologies
Platform: UNKNOWN
Classifier: Development Status :: 5 - Production/Stable
Classifier: Framework :: Django :: 2.0
Classifier: Framework :: Django :: 2.1
Classifier: Framework :: Django :: 2.2
Classifier: Intended Audience :: Developers
Classifier: License :: OSI Approved :: BSD License
Classifier: Natural Language :: English
Classifier: Programming Language :: Python :: 3
Classifier: Programming Language :: Python :: 3.5
Classifier: Programming Language :: Python :: 3.6
Requires-Dist: djangorestframework (==3.10.3)
Requires-Dist: django-filter (==2.2.0)
Requires-Dist: django-genomix (==1.1.0)
Requires-Dist: django-model-utils (==3.2.0)
Requires-Dist: pronto (==0.12.2)
